adafruit_circuitpython_motor-3.4.16.dist-info/licenses/LICENSE
adafruit_motor/__init__.py
adafruit_motor/motor.py
adafruit_motor/servo.py
adafruit_motor/stepper.py
adafruit_circuitpython_motor-3.4.16.dist-info/METADATA
adafruit_circuitpython_motor-3.4.16.dist-info/WHEEL
adafruit_circuitpython_motor-3.4.16.dist-info/top_level.txt
adafruit_circuitpython_motor-3.4.16.dist-info/RECORD
