Metadata-Version: 2.4
Name: adafruit-circuitpython-motor
Version: 3.4.16
Summary: CircuitPython helper library provides higher level objects to control motors and servos.
Author-email: Adafruit Industries <circuitpython@adafruit.com>
License: MIT
Project-URL: Homepage, https://github.com/adafruit/Adafruit_CircuitPython_Motor
Keywords: adafruit,servo,stepper,motor,hardware,micropython,circuitpython
Classifier: Intended Audience :: Developers
Classifier: Topic :: Software Development :: Libraries
Classifier: Topic :: Software Development :: Embedded Systems
Classifier: Topic :: System :: Hardware
Classifier: License :: OSI Approved :: MIT License
Classifier: Programming Language :: Python :: 3
License-File: LICENSE
Requires-Dist: Adafruit-Blinka>=7.0.0
Requires-Dist: adafruit-circuitpython-typing>=1.5.0
Provides-Extra: optional
Dynamic: license-file
